huaweicloudsdkconfig/__init__.py
huaweicloudsdkconfig/v1/__init__.py
huaweicloudsdkconfig/v1/config_async_client.py
huaweicloudsdkconfig/v1/config_client.py
huaweicloudsdkconfig/v1/model/__init__.py
huaweicloudsdkconfig/v1/model/account_aggregation_source.py
huaweicloudsdkconfig/v1/model/aggregate_compliance_detail_request.py
huaweicloudsdkconfig/v1/model/aggregate_discovered_resource_counts_request.py
huaweicloudsdkconfig/v1/model/aggregate_discovered_resources_request.py
huaweicloudsdkconfig/v1/model/aggregate_policy_assignment_detail_request.py
huaweicloudsdkconfig/v1/model/aggregate_policy_assignments.py
huaweicloudsdkconfig/v1/model/aggregate_policy_assignments_filters.py
huaweicloudsdkconfig/v1/model/aggregate_policy_assignments_request.py
huaweicloudsdkconfig/v1/model/aggregate_policy_compliance_summary_result.py
huaweicloudsdkconfig/v1/model/aggregate_policy_states_request.py
huaweicloudsdkconfig/v1/model/aggregate_resource_config_request.py
huaweicloudsdkconfig/v1/model/aggregated_source_status.py
huaweicloudsdkconfig/v1/model/aggregation_authorization_request.py
huaweicloudsdkconfig/v1/model/aggregation_authorization_resp.py
huaweicloudsdkconfig/v1/model/base_resource_entity.py
huaweicloudsdkconfig/v1/model/batch_create_remediation_exceptions_request.py
huaweicloudsdkconfig/v1/model/batch_create_remediation_exceptions_request_body.py
huaweicloudsdkconfig/v1/model/batch_create_remediation_exceptions_response.py
huaweicloudsdkconfig/v1/model/batch_delete_remediation_exceptions_request.py
huaweicloudsdkconfig/v1/model/batch_delete_remediation_exceptions_request_body.py
huaweicloudsdkconfig/v1/model/batch_delete_remediation_exceptions_response.py
huaweicloudsdkconfig/v1/model/channel_config_body.py
huaweicloudsdkconfig/v1/model/collect_all_resources_summary_request.py
huaweicloudsdkconfig/v1/model/collect_all_resources_summary_response.py
huaweicloudsdkconfig/v1/model/collect_conformance_pack_compliance_summary_request.py
huaweicloudsdkconfig-3.1.184.dist-info/METADATA
huaweicloudsdkconfig-3.1.184.dist-info/WHEEL
huaweicloudsdkconfig-3.1.184.dist-info/licenses/LICENSE
huaweicloudsdkconfig-3.1.184.dist-info/RECORD
